pyrecombine/__init__.py
pyrecombine/_recombine.cpython-311-darwin.so
pyrecombine/.dylibs/libomp.dylib
pyrecombine-1.0.1.dist-info/RECORD
pyrecombine-1.0.1.dist-info/WHEEL
pyrecombine-1.0.1.dist-info/METADATA
pyrecombine-1.0.1.dist-info/licenses/LICENSE.txt
